vnii/__init__.py
vnii-0.0.6.dist-info/METADATA
vnii-0.0.6.dist-info/WHEEL
vnii-0.0.6.dist-info/top_level.txt
vnii-0.0.6.dist-info/RECORD
